README.md
setup.py
AWSOM/AWSOM.py
AWSOM/AWSOM_config.py
AWSOM/__init__.py
AWSOM/reference_code_batches.py
AWSOM/reference_code_demo.py
AWSOM/reference_code_ui.py
AWSOM/test_AWSOM.py
AWSOM.egg-info/PKG-INFO
AWSOM.egg-info/SOURCES.txt
AWSOM.egg-info/dependency_links.txt
AWSOM.egg-info/requires.txt
AWSOM.egg-info/top_level.txt