Metadata-Version: 2.1
Name: AWSOM
Version: 0.14
Summary: Desktop automation tools for managing common tasks such as renaming media files and making backups, as well as interacting with Adobe Premiere Pro using the `Pymiere` library (Windows only).
Home-page: https://github.com/pfython/AWSOM
Author: Peter Fison
Author-email: peter@southwestlondon.tv
License: MIT
Download-URL: https://github.com/pfython/AWSOM/archive/0.14.tar.gz
Keywords: AWSOM,search,video,audio,media,AWSOM,TV,content,manage,organise,organize,Premiere,Adobe,Pymiere,YouTube,metadata,workflow,automation,Creative Cloud,edit,editor,editing
Platform: UNKNOWN
Classifier: Development Status :: 3 - Alpha
Classifier: Intended Audience :: Developers
Classifier: Intended Audience :: End Users/Desktop
Classifier: License :: OSI Approved :: MIT License
Classifier: Natural Language :: English
Classifier: Operating System :: Microsoft :: Windows :: Windows 10
Classifier: Programming Language :: Python :: 3.6
Classifier: Programming Language :: Python :: 3.7
Classifier: Programming Language :: Python :: 3.8
Classifier: Programming Language :: Python :: 3.9
Classifier: Topic :: Multimedia
Classifier: Topic :: Multimedia :: Video
Classifier: Topic :: Multimedia :: Video :: Non-Linear Editor
